thegame/__init__.py
thegame-1.7.dist-info/DESCRIPTION.rst
thegame-1.7.dist-info/METADATA
thegame-1.7.dist-info/RECORD
thegame-1.7.dist-info/WHEEL
thegame-1.7.dist-info/metadata.json
thegame-1.7.dist-info/top_level.txt
